<annotation>
	<folder></folder>
	<filename>020fcce8dd0c0653_jpg.rf.17e882b8976d3612fda49a160d98c611.jpg</filename>
	<path>020fcce8dd0c0653_jpg.rf.17e882b8976d3612fda49a160d98c611.jpg</path>
	<source>
		<database>roboflow.ai</database>
	</source>
	<size>
		<width>416</width>
		<height>416</height>
		<depth>3</depth>
	</size>
	<segmented>0</segmented>
	<object>
		<name>bus</name>
		<pose>Unspecified</pose>
		<truncated>0</truncated>
		<difficult>0</difficult>
		<occluded>0</occluded>
		<bndbox>
			<xmin>227</xmin>
			<xmax>334</xmax>
			<ymin>167</ymin>
			<ymax>364</ymax>
		</bndbox>
	</object>
	<object>
		<name>bus</name>
		<pose>Unspecified</pose>
		<truncated>0</truncated>
		<difficult>0</difficult>
		<occluded>0</occluded>
		<bndbox>
			<xmin>110</xmin>
			<xmax>212</xmax>
			<ymin>176</ymin>
			<ymax>325</ymax>
		</bndbox>
	</object>
	<object>
		<name>bus</name>
		<pose>Unspecified</pose>
		<truncated>0</truncated>
		<difficult>0</difficult>
		<occluded>0</occluded>
		<bndbox>
			<xmin>9</xmin>
			<xmax>122</xmax>
			<ymin>173</ymin>
			<ymax>327</ymax>
		</bndbox>
	</object>
	<object>
		<name>bus</name>
		<pose>Unspecified</pose>
		<truncated>0</truncated>
		<difficult>0</difficult>
		<occluded>0</occluded>
		<bndbox>
			<xmin>331</xmin>
			<xmax>407</xmax>
			<ymin>181</ymin>
			<ymax>324</ymax>
		</bndbox>
	</object>
</annotation>
