<annotation>
	<folder></folder>
	<filename>089cc41a901b2653_jpg.rf.f9d8ab53b0e9477a77f01ca841ceadf5.jpg</filename>
	<path>089cc41a901b2653_jpg.rf.f9d8ab53b0e9477a77f01ca841ceadf5.jpg</path>
	<source>
		<database>roboflow.ai</database>
	</source>
	<size>
		<width>416</width>
		<height>416</height>
		<depth>3</depth>
	</size>
	<segmented>0</segmented>
	<object>
		<name>car</name>
		<pose>Unspecified</pose>
		<truncated>0</truncated>
		<difficult>0</difficult>
		<occluded>0</occluded>
		<bndbox>
			<xmin>65</xmin>
			<xmax>189</xmax>
			<ymin>238</ymin>
			<ymax>355</ymax>
		</bndbox>
	</object>
	<object>
		<name>car</name>
		<pose>Unspecified</pose>
		<truncated>0</truncated>
		<difficult>0</difficult>
		<occluded>0</occluded>
		<bndbox>
			<xmin>214</xmin>
			<xmax>410</xmax>
			<ymin>88</ymin>
			<ymax>299</ymax>
		</bndbox>
	</object>
	<object>
		<name>ambulance</name>
		<pose>Unspecified</pose>
		<truncated>0</truncated>
		<difficult>0</difficult>
		<occluded>0</occluded>
		<bndbox>
			<xmin>147</xmin>
			<xmax>247</xmax>
			<ymin>174</ymin>
			<ymax>280</ymax>
		</bndbox>
	</object>
	<object>
		<name>ambulance</name>
		<pose>Unspecified</pose>
		<truncated>0</truncated>
		<difficult>0</difficult>
		<occluded>0</occluded>
		<bndbox>
			<xmin>130</xmin>
			<xmax>181</xmax>
			<ymin>223</ymin>
			<ymax>283</ymax>
		</bndbox>
	</object>
	<object>
		<name>ambulance</name>
		<pose>Unspecified</pose>
		<truncated>0</truncated>
		<difficult>0</difficult>
		<occluded>0</occluded>
		<bndbox>
			<xmin>36</xmin>
			<xmax>83</xmax>
			<ymin>279</ymin>
			<ymax>328</ymax>
		</bndbox>
	</object>
</annotation>
