<annotation>
	<folder></folder>
	<filename>723f1dec45f28293_jpg.rf.8401d0fc780128d50ec924b8ab3b10a7.jpg</filename>
	<path>723f1dec45f28293_jpg.rf.8401d0fc780128d50ec924b8ab3b10a7.jpg</path>
	<source>
		<database>roboflow.ai</database>
	</source>
	<size>
		<width>416</width>
		<height>416</height>
		<depth>3</depth>
	</size>
	<segmented>0</segmented>
	<object>
		<name>bus</name>
		<pose>Unspecified</pose>
		<truncated>0</truncated>
		<difficult>0</difficult>
		<occluded>0</occluded>
		<bndbox>
			<xmin>16</xmin>
			<xmax>378</xmax>
			<ymin>20</ymin>
			<ymax>386</ymax>
		</bndbox>
	</object>
</annotation>
