<annotation>
	<folder></folder>
	<filename>d24ca593fdb348fc_jpg.rf.e31a7f60f0999118dcb6d957b79edbb6.jpg</filename>
	<path>d24ca593fdb348fc_jpg.rf.e31a7f60f0999118dcb6d957b79edbb6.jpg</path>
	<source>
		<database>roboflow.ai</database>
	</source>
	<size>
		<width>416</width>
		<height>416</height>
		<depth>3</depth>
	</size>
	<segmented>0</segmented>
	<object>
		<name>ambulance</name>
		<pose>Unspecified</pose>
		<truncated>0</truncated>
		<difficult>0</difficult>
		<occluded>0</occluded>
		<bndbox>
			<xmin>48</xmin>
			<xmax>179</xmax>
			<ymin>112</ymin>
			<ymax>248</ymax>
		</bndbox>
	</object>
</annotation>
